cmd_iac/__init__.py
cmd_iac/__main__.py
Qualys_IaC_Security-1.0.6.dist-info/LICENSE
Qualys_IaC_Security-1.0.6.dist-info/METADATA
Qualys_IaC_Security-1.0.6.dist-info/WHEEL
Qualys_IaC_Security-1.0.6.dist-info/entry_points.txt
Qualys_IaC_Security-1.0.6.dist-info/top_level.txt
Qualys_IaC_Security-1.0.6.dist-info/RECORD
