Metadata-Version: 2.1
Name: Qualys-IaC-Security
Version: 1.0.6
Summary: Command line interface to scan Infrastructure-as-Code templates using Qualys IaC.
Author: qualys
Author-email: plugins@qualys.com
License: MIT
Keywords: qiac
Classifier: Programming Language :: Python :: 3
Classifier: Development Status :: 5 - Production/Stable
Requires-Python: >=3
License-File: LICENSE
Requires-Dist: click (==8.0.1)
Requires-Dist: requests (==2.31.0)
Requires-Dist: click-option-group (==0.5.3)
Requires-Dist: zipp (==3.4.1)
Requires-Dist: prettytable (==2.1.0)
Requires-Dist: py7zr (==0.20.2)
Requires-Dist: pyyaml (==6.0.1)
Requires-Dist: gzinfo (==1.0.2)
Requires-Dist: cryptography (==41.0.3)
